setup.py
astviz/Ast.ebnf
astviz/__init__.py
astviz/astparser.py
astviz/astviz.py
astviz.egg-info/PKG-INFO
astviz.egg-info/SOURCES.txt
astviz.egg-info/dependency_links.txt
astviz.egg-info/entry_points.txt
astviz.egg-info/requires.txt
astviz.egg-info/top_level.txt