Metadata-Version: 1.1
Name: astviz
Version: 0.1.1
Summary: Simple Ast Visualization Tool
Home-page: http://github.com/compiler-dept/astviz
Author: Robert Heumueller
Author-email: code@heum.de
License: MIT
Download-URL: https://github.com/compiler-dept/astviz/archive/master.zip
Platform: UNKNOWN
